bert_score/__init__.py
bert_score/score.py
bert_score/scorer.py
bert_score/utils.py
bert_score/rescale_baseline/cs/bert-base-multilingual-cased.tsv
bert_score/rescale_baseline/cs/xlm-mlm-100-1280.tsv
bert_score/rescale_baseline/cs/xlm-roberta-base.tsv
bert_score/rescale_baseline/cs/xlm-roberta-large.tsv
bert_score/rescale_baseline/de/bert-base-multilingual-cased.tsv
bert_score/rescale_baseline/de/xlm-mlm-100-1280.tsv
bert_score/rescale_baseline/de/xlm-roberta-base.tsv
bert_score/rescale_baseline/de/xlm-roberta-large.tsv
bert_score/rescale_baseline/en/albert-base-v1.tsv
bert_score/rescale_baseline/en/albert-base-v2.tsv
bert_score/rescale_baseline/en/albert-large-v1.tsv
bert_score/rescale_baseline/en/albert-large-v2.tsv
bert_score/rescale_baseline/en/albert-xlarge-v1.tsv
bert_score/rescale_baseline/en/albert-xlarge-v2.tsv
bert_score/rescale_baseline/en/albert-xxlarge-v1.tsv
bert_score/rescale_baseline/en/albert-xxlarge-v2.tsv
bert_score/rescale_baseline/en/bert-base-cased-finetuned-mrpc.tsv
bert_score/rescale_baseline/en/bert-base-multilingual-cased.tsv
bert_score/rescale_baseline/en/bert-base-uncased.tsv
bert_score/rescale_baseline/en/bert-large-uncased.tsv
bert_score/rescale_baseline/en/distilbert-base-multilingual-cased.tsv
bert_score/rescale_baseline/en/distilbert-base-uncased-distilled-squad.tsv
bert_score/rescale_baseline/en/distilbert-base-uncased.tsv
bert_score/rescale_baseline/en/distilroberta-base.tsv
bert_score/rescale_baseline/en/roberta-base.tsv
bert_score/rescale_baseline/en/roberta-large-mnli.tsv
bert_score/rescale_baseline/en/roberta-large.tsv
bert_score/rescale_baseline/en/xlm-mlm-100-1280.tsv
bert_score/rescale_baseline/en/xlm-mlm-en-2048.tsv
bert_score/rescale_baseline/en/xlm-roberta-base.tsv
bert_score/rescale_baseline/en/xlm-roberta-large.tsv
bert_score/rescale_baseline/en/xlnet-base-cased.tsv
bert_score/rescale_baseline/en/xlnet-large-cased.tsv
bert_score/rescale_baseline/en/microsoft/deberta-base-mnli.tsv
xtest_bert_score-0.3.13.1.dist-info/licenses/LICENSE
xtest_bert_score-0.3.13.1.dist-info/METADATA
xtest_bert_score-0.3.13.1.dist-info/WHEEL
xtest_bert_score-0.3.13.1.dist-info/entry_points.txt
xtest_bert_score-0.3.13.1.dist-info/top_level.txt
xtest_bert_score-0.3.13.1.dist-info/RECORD
