Metadata-Version: 2.4
Name: xtest_bert_score
Version: 0.3.13.1
Summary: PyTorch implementation of BERT score for xtest
Home-page: https://github.com/Tiiiger/bert_score
Author: Tianyi Zhang*, Varsha Kishore*, Felix Wu*, Kilian Q. Weinberger, and Yoav Artzi
Author-email: tzhang@asapp.com
License: MIT
Keywords: BERT NLP deep learning google metric
Classifier: Intended Audience :: Science/Research
Classifier: License :: OSI Approved :: MIT License
Classifier: Programming Language :: Python :: 3
Classifier: Topic :: Scientific/Engineering :: Artificial Intelligence
Requires-Python: >=3.6
License-File: LICENSE
Requires-Dist: torch>=1.0.0
Requires-Dist: pandas>=1.0.1
Requires-Dist: transformers>=3.0.0
Requires-Dist: numpy
Requires-Dist: requests
Requires-Dist: tqdm>=4.31.1
Requires-Dist: matplotlib
Requires-Dist: packaging>=20.9
Dynamic: author
Dynamic: author-email
Dynamic: classifier
Dynamic: description
Dynamic: description-content-type
Dynamic: home-page
Dynamic: keywords
Dynamic: license
Dynamic: license-file
Dynamic: requires-dist
Dynamic: requires-python
Dynamic: summary
